retry/__init__.py
retry/api.py
retry_sh-1.0.5.dist-info/AUTHORS
retry_sh-1.0.5.dist-info/LICENSE
retry_sh-1.0.5.dist-info/METADATA
retry_sh-1.0.5.dist-info/WHEEL
retry_sh-1.0.5.dist-info/top_level.txt
retry_sh-1.0.5.dist-info/RECORD
