Metadata-Version: 2.1
Name: retry-sh
Version: 1.0.5
Summary: Easy to use retry decorator.
Home-page: https://github.com/shizacat/retry
Author: invl, Alexey Matveev
Author-email: shizacat@yandex.ru
License: Apache License 2.0
Classifier: Intended Audience :: Developers
Classifier: License :: OSI Approved :: Apache Software License
Classifier: Natural Language :: English
Classifier: Operating System :: OS Independent
Classifier: Programming Language :: Python
Classifier: Programming Language :: Python :: 3
Classifier: Programming Language :: Python :: 3.6
Classifier: Programming Language :: Python :: 3.7
Classifier: Programming Language :: Python :: 3.8
Classifier: Programming Language :: Python :: 3.9
Classifier: Programming Language :: Python :: 3.10
Classifier: Topic :: Software Development
Requires-Python: >=3.6
License-File: LICENSE
License-File: AUTHORS
Requires-Dist: decorator (>=5)
